odoo10_addon_bus_presence_override-10.0.1.0.0.99.dev2-py2.7-nspkg.pth
odoo/addons/bus_presence_override/README.rst
odoo/addons/bus_presence_override/__init__.py
odoo/addons/bus_presence_override/__manifest__.py
odoo/addons/bus_presence_override/status_constants.py
odoo/addons/bus_presence_override/controllers/__init__.py
odoo/addons/bus_presence_override/controllers/main.py
odoo/addons/bus_presence_override/i18n/bus_presence_override.pot
odoo/addons/bus_presence_override/models/__init__.py
odoo/addons/bus_presence_override/models/bus_presence.py
odoo/addons/bus_presence_override/models/res_partner.py
odoo/addons/bus_presence_override/models/res_users.py
odoo/addons/bus_presence_override/static/description/icon.png
odoo/addons/bus_presence_override/static/src/js/bus_presence_systray.js
odoo/addons/bus_presence_override/static/src/less/bus_presence_systray.less
odoo/addons/bus_presence_override/static/src/xml/bus_presence_systray.xml
odoo/addons/bus_presence_override/tests/__init__.py
odoo/addons/bus_presence_override/tests/bus_setup.py
odoo/addons/bus_presence_override/tests/test_bus_presence.py
odoo/addons/bus_presence_override/tests/test_res_partner.py
odoo/addons/bus_presence_override/tests/test_res_users.py
odoo/addons/bus_presence_override/views/assets.xml
odoo10_addon_bus_presence_override-10.0.1.0.0.99.dev2.dist-info/METADATA
odoo10_addon_bus_presence_override-10.0.1.0.0.99.dev2.dist-info/RECORD
odoo10_addon_bus_presence_override-10.0.1.0.0.99.dev2.dist-info/WHEEL
odoo10_addon_bus_presence_override-10.0.1.0.0.99.dev2.dist-info/namespace_packages.txt
odoo10_addon_bus_presence_override-10.0.1.0.0.99.dev2.dist-info/top_level.txt
